sqlfluff_templater_dbt/__init__.py
sqlfluff_templater_dbt/templater.py
sqlfluff_templater_dbt-3.5.0.dist-info/licenses/LICENSE.md
sqlfluff_templater_dbt-3.5.0.dist-info/METADATA
sqlfluff_templater_dbt-3.5.0.dist-info/WHEEL
sqlfluff_templater_dbt-3.5.0.dist-info/entry_points.txt
sqlfluff_templater_dbt-3.5.0.dist-info/top_level.txt
sqlfluff_templater_dbt-3.5.0.dist-info/RECORD
