Metadata-Version: 2.4
Name: sqlfluff-templater-dbt
Version: 3.5.0
Summary: Lint your dbt project SQL
Author-email: Alan Cruickshank <alan@designingoverload.com>
License: MIT License
Project-URL: Homepage, https://www.sqlfluff.com
Project-URL: Documentation, https://docs.sqlfluff.com
Project-URL: Source, https://github.com/sqlfluff/sqlfluff
Project-URL: Changes, https://github.com/sqlfluff/sqlfluff/blob/main/CHANGELOG.md
Project-URL: Issue Tracker, https://github.com/sqlfluff/sqlfluff/issues
Project-URL: Twitter, https://twitter.com/SQLFluff
Project-URL: Chat, https://github.com/sqlfluff/sqlfluff#sqlfluff-on-slack
Keywords: sqlfluff,sql,linter,formatter,bigquery,clickhouse,databricks,db2,duckdb,exasol,greenplum,hive,materialize,mysql,postgres,redshift,snowflake,soql,sparksql,sqlite,teradata,tsql,dbt
Classifier: Development Status :: 5 - Production/Stable
Classifier: Environment :: Console
Classifier: Intended Audience :: Developers
Classifier: License :: OSI Approved :: MIT License
Classifier: Operating System :: Unix
Classifier: Operating System :: POSIX
Classifier: Operating System :: MacOS
Classifier: Operating System :: Microsoft :: Windows
Classifier: Programming Language :: Python
Classifier: Programming Language :: Python :: 3
Classifier: Programming Language :: Python :: 3.9
Classifier: Programming Language :: Python :: 3.10
Classifier: Programming Language :: Python :: 3.11
Classifier: Programming Language :: Python :: 3.12
Classifier: Programming Language :: Python :: 3.13
Classifier: Programming Language :: Python :: Implementation :: CPython
Classifier: Topic :: Utilities
Classifier: Topic :: Software Development :: Quality Assurance
License-File: LICENSE.md
Requires-Dist: sqlfluff==3.5.0
Requires-Dist: dbt-core>=1.4.1
Requires-Dist: jinja2-simple-tags>=0.3.1
Dynamic: license-file
